xbench/__init__.py
xbench/example.py
xbench/fmt.py
xbench/schema.py
xbench/types.py
xbench/utils.py
xbench/version.py
xbench/xl.py
xbench/cmd/__init__.py
xbench/cmd/__main__.py
xbench/cmd/bootstrap.py
xbench/cmd/capture.py
xbench/cmd/evaluate.py
xbench/cmd/generate.py
xbench/cmd/snapshot.py
xbench/cmd/utils.py
xbench/docs/__init__.py
xbench/docs/d1.py
xbench/docs/d2.py
xbench/docs/doc_type.py
xbench/docs/templates/d1.xlsx
xbench/docs/templates/d2.xlsx
xbench/tools/__init__.py
xbench/tools/impira.py
xbench/tools/textract.py
xbench/tools/tool.py
xbench-0.0.3.dist-info/LICENSE
xbench-0.0.3.dist-info/METADATA
xbench-0.0.3.dist-info/WHEEL
xbench-0.0.3.dist-info/entry_points.txt
xbench-0.0.3.dist-info/top_level.txt
xbench-0.0.3.dist-info/RECORD
