Metadata-Version: 2.1
Name: xbench
Version: 0.0.3
Summary: Document Extraction Benchmark (xbench)
Home-page: https://github.com/impira/extraction-benchmark
Author: Impira Engineering
Author-email: engineering@impira.com
License: UNKNOWN
Project-URL: Bug Tracker, https://github.com/impira/extraction-benchmark/issues
Platform: UNKNOWN
Classifier: Programming Language :: Python :: 3
Classifier: License :: OSI Approved :: MIT License
Classifier: Operating System :: OS Independent
Requires-Python: >=3.8
License-File: LICENSE
Requires-Dist: pydantic
Requires-Dist: typing
Requires-Dist: typing-extensions
Requires-Dist: faker (==8.13.2)
Requires-Dist: openpyxl
Requires-Dist: Pillow (>=8)
Requires-Dist: pdf2image
Requires-Dist: numpy
Requires-Dist: impira (==0.1.7)
Requires-Dist: boto3
Requires-Dist: textract-trp
Requires-Dist: requests
Requires-Dist: myst-parser (>=0.15)
Requires-Dist: sphinx (>=4.3)
